{"otherdata": {}, "traceEvents": [ {},{
"cat": "function",
"dur": 0,
"name": "__cdecl fe::MainEventDispacher::MainEventDispacher(void)",
"ph": "X",
"pid": 0,
"tid": 51076,
"ts": 53038610391.200
},{
"cat": "function",
"dur": 1,
"name": "__cdecl fe::LayerStack::LayerStack(void)",
"ph": "X",
"pid": 0,
"tid": 51076,
"ts": 53038610469.900
},{
"cat": "function",
"dur": 57180,
"name": "GLFW_Initialization",
"ph": "X",
"pid": 0,
"tid": 51076,
"ts": 53038610566.300
},{
"cat": "function",
"dur": 222505,
"name": "GLFW_CreateWindow",
"ph": "X",
"pid": 0,
"tid": 51076,
"ts": 53038667831.800
},{
"cat": "function",
"dur": 4434,
"name": "void __cdecl fe::Win10Window::SetGLFWEventsCallbacks(void)",
"ph": "X",
"pid": 0,
"tid": 51076,
"ts": 53038890448.700
},{
"cat": "function",
"dur": 284371,
"name": "void __cdecl fe::Win10Window::Init(const struct fe::WindowAttributes &)",
"ph": "X",
"pid": 0,
"tid": 51076,
"ts": 53038610565.300
},{
"cat": "function",
"dur": 284406,
"name": "__cdecl fe::Win10Window::Win10Window(const struct fe::WindowAttributes &)",
"ph": "X",
"pid": 0,
"tid": 51076,
"ts": 53038610562.600
},{
"cat": "function",
"dur": 284491,
"name": "class std::unique_ptr<class fe::Window,struct std::default_delete<class fe::Window> > __cdecl fe::Window::Create(const struct fe::WindowAttributes &)",
"ph": "X",
"pid": 0,
"tid": 51076,
"ts": 53038610508.000
},{
"cat": "function",
"dur": 1,
"name": "__cdecl fe::OpenGLRenderingContext::OpenGLRenderingContext(struct GLFWwindow *)",
"ph": "X",
"pid": 0,
"tid": 51076,
"ts": 53038895183.900
},{
"cat": "function",
"dur": 15207,
"name": "void __cdecl fe::OpenGLRenderingContext::Init(void)",
"ph": "X",
"pid": 0,
"tid": 51076,
"ts": 53038895246.200
},{
"cat": "function",
"dur": 607,
"name": "void __cdecl fe::Win10Window::SetVSync(bool)",
"ph": "X",
"pid": 0,
"tid": 51076,
"ts": 53038910511.200
},{
"cat": "function",
"dur": 16104,
"name": "void __cdecl fe::Win10Window::CreateRenderingContext(enum fe::GDIType)",
"ph": "X",
"pid": 0,
"tid": 51076,
"ts": 53038895057.900
},{
"cat": "function",
"dur": 0,
"name": "__cdecl fe::Layer::Layer(const class std::basic_string<char,struct std::char_traits<char>,class std::allocator<char> > &)",
"ph": "X",
"pid": 0,
"tid": 51076,
"ts": 53038911221.600
},{
"cat": "function",
"dur": 0,
"name": "__cdecl fe::ApplicationLayer::ApplicationLayer(class std::function<void __cdecl(class std::shared_ptr<class fe::Events::Event>)>)",
"ph": "X",
"pid": 0,
"tid": 51076,
"ts": 53038911264.300
},{
"cat": "function",
"dur": 482,
"name": "void __cdecl fe::LayerStack::PushOuterLayer(class std::shared_ptr<class fe::Layer>)",
"ph": "X",
"pid": 0,
"tid": 51076,
"ts": 53038911300.200
},{
"cat": "function",
"dur": 0,
"name": "__cdecl fe::Layer::Layer(const class std::basic_string<char,struct std::char_traits<char>,class std::allocator<char> > &)",
"ph": "X",
"pid": 0,
"tid": 51076,
"ts": 53038911828.000
},{
"cat": "function",
"dur": 0,
"name": "__cdecl fe::ImGuiLayer::ImGuiLayer(void)",
"ph": "X",
"pid": 0,
"tid": 51076,
"ts": 53038911859.000
},{
"cat": "function",
"dur": 404,
"name": "void __cdecl fe::ImGuiLayer::OnAttach(void)",
"ph": "X",
"pid": 0,
"tid": 51076,
"ts": 53038912497.400
},{
"cat": "function",
"dur": 1060,
"name": "void __cdecl fe::LayerStack::PushOuterLayer(class std::shared_ptr<class fe::Layer>)",
"ph": "X",
"pid": 0,
"tid": 51076,
"ts": 53038911890.100
},{
"cat": "function",
"dur": 0,
"name": "void __cdecl fe::Renderer::Init(void)",
"ph": "X",
"pid": 0,
"tid": 51076,
"ts": 53038912988.300
},{
"cat": "function",
"dur": 163,
"name": "void __cdecl fe::Renderer::CreateAPI(enum fe::GDIType)",
"ph": "X",
"pid": 0,
"tid": 51076,
"ts": 53038913021.700
},{
"cat": "function",
"dur": 61370,
"name": "OpenGL shader compilation",
"ph": "X",
"pid": 0,
"tid": 51076,
"ts": 53038913986.000
},{
"cat": "function",
"dur": 61549,
"name": "Shader compilation",
"ph": "X",
"pid": 0,
"tid": 51076,
"ts": 53038913917.100
},{
"cat": "function",
"dur": 435,
"name": "OpenGL shader compilation",
"ph": "X",
"pid": 0,
"tid": 51076,
"ts": 53038975564.200
},{
"cat": "function",
"dur": 498,
"name": "Shader compilation",
"ph": "X",
"pid": 0,
"tid": 51076,
"ts": 53038975551.000
},{
"cat": "function",
"dur": 1564,
"name": "OpenGL Shader linking",
"ph": "X",
"pid": 0,
"tid": 51076,
"ts": 53038976095.900
},{
"cat": "function",
"dur": 63797,
"name": "void __cdecl fe::OpenGLShader::Compile(const class std::unordered_map<unsigned int,class std::basic_string<char,struct std::char_traits<char>,class std::allocator<char> >,struct std::hash<unsigned int>,struct std::equal_to<unsigned int>,class std::allocator<struct std::pair<unsigned int const ,class std::basic_string<char,struct std::char_traits<char>,class std::allocator<char> > > > > &)",
"ph": "X",
"pid": 0,
"tid": 51076,
"ts": 53038913916.800
},{
"cat": "function",
"dur": 64059,
"name": "__cdecl fe::OpenGLShader::OpenGLShader(const class std::basic_string<char,struct std::char_traits<char>,class std::allocator<char> > &)",
"ph": "X",
"pid": 0,
"tid": 51076,
"ts": 53038913696.300
},{
"cat": "function",
"dur": 465,
"name": "OpenGL shader compilation",
"ph": "X",
"pid": 0,
"tid": 51076,
"ts": 53038978028.900
},{
"cat": "function",
"dur": 521,
"name": "Shader compilation",
"ph": "X",
"pid": 0,
"tid": 51076,
"ts": 53038978021.500
},{
"cat": "function",
"dur": 429,
"name": "OpenGL shader compilation",
"ph": "X",
"pid": 0,
"tid": 51076,
"ts": 53038978578.400
},{
"cat": "function",
"dur": 481,
"name": "Shader compilation",
"ph": "X",
"pid": 0,
"tid": 51076,
"ts": 53038978572.600
},{
"cat": "function",
"dur": 1258,
"name": "OpenGL Shader linking",
"ph": "X",
"pid": 0,
"tid": 51076,
"ts": 53038979088.200
},{
"cat": "function",
"dur": 2381,
"name": "void __cdecl fe::OpenGLShader::Compile(const class std::unordered_map<unsigned int,class std::basic_string<char,struct std::char_traits<char>,class std::allocator<char> >,struct std::hash<unsigned int>,struct std::equal_to<unsigned int>,class std::allocator<struct std::pair<unsigned int const ,class std::basic_string<char,struct std::char_traits<char>,class std::allocator<char> > > > > &)",
"ph": "X",
"pid": 0,
"tid": 51076,
"ts": 53038978021.200
},{
"cat": "function",
"dur": 2581,
"name": "__cdecl fe::OpenGLShader::OpenGLShader(const class std::basic_string<char,struct std::char_traits<char>,class std::allocator<char> > &)",
"ph": "X",
"pid": 0,
"tid": 51076,
"ts": 53038977859.200
},{
"cat": "function",
"dur": 67918,
"name": "void __cdecl fe::Renderer::InitAPI(enum fe::GDIType)",
"ph": "X",
"pid": 0,
"tid": 51076,
"ts": 53038913232.400
},{
"cat": "function",
"dur": 13,
"name": "__cdecl fe::OpenGLVertexArray::OpenGLVertexArray(void)",
"ph": "X",
"pid": 0,
"tid": 51076,
"ts": 53038987488.900
},{
"cat": "function",
"dur": 31,
"name": "__cdecl fe::OpenGLVertexBuffer::OpenGLVertexBuffer(unsigned int)",
"ph": "X",
"pid": 0,
"tid": 51076,
"ts": 53038987578.700
},{
"cat": "function",
"dur": 90,
"name": "class std::unique_ptr<class fe::VertexBuffer,struct std::default_delete<class fe::VertexBuffer> > __cdecl fe::VertexBuffer::Create(unsigned int)",
"ph": "X",
"pid": 0,
"tid": 51076,
"ts": 53038987564.700
},{
"cat": "function",
"dur": 0,
"name": "__cdecl fe::BufferLayout::BufferLayout(const class std::initializer_list<class fe::BufferElement> &)",
"ph": "X",
"pid": 0,
"tid": 51076,
"ts": 53038987709.000
},{
"cat": "function",
"dur": 3,
"name": "void __cdecl fe::OpenGLVertexBuffer::SetLayout(const class fe::BufferLayout &)",
"ph": "X",
"pid": 0,
"tid": 51076,
"ts": 53038987743.000
},{
"cat": "function",
"dur": 0,
"name": "void __cdecl fe::OpenGLVertexBuffer::Bind(void) const",
"ph": "X",
"pid": 0,
"tid": 51076,
"ts": 53038987788.200
},{
"cat": "function",
"dur": 0,
"name": "const class fe::BufferLayout &__cdecl fe::OpenGLVertexBuffer::GetLayout(void) const",
"ph": "X",
"pid": 0,
"tid": 51076,
"ts": 53038987821.200
},{
"cat": "function",
"dur": 87,
"name": "void __cdecl fe::OpenGLVertexArray::AddVertexBuffer(const class std::shared_ptr<class fe::VertexBuffer> &)",
"ph": "X",
"pid": 0,
"tid": 51076,
"ts": 53038987787.200
},{
"cat": "function",
"dur": 126,
"name": "__cdecl fe::OpenGLIndexBuffer::OpenGLIndexBuffer(unsigned int *,unsigned int)",
"ph": "X",
"pid": 0,
"tid": 51076,
"ts": 53038990328.400
},{
"cat": "function",
"dur": 170,
"name": "class std::unique_ptr<class fe::IndexBuffer,struct std::default_delete<class fe::IndexBuffer> > __cdecl fe::IndexBuffer::Create(unsigned int *,unsigned int)",
"ph": "X",
"pid": 0,
"tid": 51076,
"ts": 53038990327.600
},{
"cat": "function",
"dur": 1,
"name": "void __cdecl fe::OpenGLIndexBuffer::Bind(void) const",
"ph": "X",
"pid": 0,
"tid": 51076,
"ts": 53038990530.500
},{
"cat": "function",
"dur": 32,
"name": "void __cdecl fe::OpenGLVertexArray::SetIndexBuffer(const class std::shared_ptr<class fe::IndexBuffer> &)",
"ph": "X",
"pid": 0,
"tid": 51076,
"ts": 53038990529.800
},{
"cat": "function",
"dur": 527,
"name": "OpenGL shader compilation",
"ph": "X",
"pid": 0,
"tid": 51076,
"ts": 53038990783.300
},{
"cat": "function",
"dur": 592,
"name": "Shader compilation",
"ph": "X",
"pid": 0,
"tid": 51076,
"ts": 53038990768.700
},{
"cat": "function",
"dur": 458,
"name": "OpenGL shader compilation",
"ph": "X",
"pid": 0,
"tid": 51076,
"ts": 53038991407.600
},{
"cat": "function",
"dur": 517,
"name": "Shader compilation",
"ph": "X",
"pid": 0,
"tid": 51076,
"ts": 53038991395.600
},{
"cat": "function",
"dur": 1356,
"name": "OpenGL Shader linking",
"ph": "X",
"pid": 0,
"tid": 51076,
"ts": 53038991946.200
},{
"cat": "function",
"dur": 2590,
"name": "void __cdecl fe::OpenGLShader::Compile(const class std::unordered_map<unsigned int,class std::basic_string<char,struct std::char_traits<char>,class std::allocator<char> >,struct std::hash<unsigned int>,struct std::equal_to<unsigned int>,class std::allocator<struct std::pair<unsigned int const ,class std::basic_string<char,struct std::char_traits<char>,class std::allocator<char> > > > > &)",
"ph": "X",
"pid": 0,
"tid": 51076,
"ts": 53038990768.300
},{
"cat": "function",
"dur": 2797,
"name": "__cdecl fe::OpenGLShader::OpenGLShader(const class std::basic_string<char,struct std::char_traits<char>,class std::allocator<char> > &)",
"ph": "X",
"pid": 0,
"tid": 51076,
"ts": 53038990607.700
},{
"cat": "function",
"dur": 12260,
"name": "void __cdecl fe::Renderer::SetAPI(enum fe::GDIType)",
"ph": "X",
"pid": 0,
"tid": 51076,
"ts": 53038981199.100
},{
"cat": "function",
"dur": 382987,
"name": "__cdecl fe::Application::Application(const class std::basic_string<char,struct std::char_traits<char>,class std::allocator<char> > &)",
"ph": "X",
"pid": 0,
"tid": 51076,
"ts": 53038610506.600
},{
"cat": "function",
"dur": 0,
"name": "__cdecl fe::Layer::Layer(const class std::basic_string<char,struct std::char_traits<char>,class std::allocator<char> > &)",
"ph": "X",
"pid": 0,
"tid": 51076,
"ts": 53038993523.400
},{
"cat": "function",
"dur": 19,
"name": "void __cdecl fe::OrthographicCamera::RecalculateViewMatrix(void)",
"ph": "X",
"pid": 0,
"tid": 51076,
"ts": 53038993577.700
},{
"cat": "function",
"dur": 65,
"name": "__cdecl fe::OrthographicCamera::OrthographicCamera(float,float,float,float)",
"ph": "X",
"pid": 0,
"tid": 51076,
"ts": 53038993568.900
},{
"cat": "function",
"dur": 51,
"name": "class std::unique_ptr<class fe::Framebuffer,struct std::default_delete<class fe::Framebuffer> > __cdecl fe::Framebuffer::Create(const struct fe::FramebufferSpecification &)",
"ph": "X",
"pid": 0,
"tid": 51076,
"ts": 53038993813.300
},{
"cat": "function",
"dur": 1506,
"name": "void __cdecl fe::LayerStack::PushOuterLayer(class std::shared_ptr<class fe::Layer>)",
"ph": "X",
"pid": 0,
"tid": 51076,
"ts": 53038993675.800
}]}