{"otherdata": {}, "traceEvents": [ {},{
"cat": "function",
"dur": 0,
"name": "__cdecl fe::Application::~Application(void)",
"ph": "X",
"pid": 0,
"tid": 27960,
"ts": 105199543735.200,
"args":{}},{
"cat": "function",
"dur": 577,
"name": "void __cdecl fe::ImGuiLayer::OnDetach(void)",
"ph": "X",
"pid": 0,
"tid": 27960,
"ts": 105199543797.500,
"args":{}},{
"cat": "function",
"dur": 194,
"name": "__cdecl fe::CActorData::~CActorData(void)",
"ph": "X",
"pid": 0,
"tid": 27960,
"ts": 105199544543.600,
"args":{}},{
"cat": "function",
"dur": 388,
"name": "__cdecl fe::CActorData::~CActorData(void)",
"ph": "X",
"pid": 0,
"tid": 27960,
"ts": 105199544787.600,
"args":{}},{
"cat": "function",
"dur": 395,
"name": "__cdecl fe::CActorData::~CActorData(void)",
"ph": "X",
"pid": 0,
"tid": 27960,
"ts": 105199545220.200,
"args":{}},{
"cat": "function",
"dur": 400,
"name": "__cdecl fe::CActorData::~CActorData(void)",
"ph": "X",
"pid": 0,
"tid": 27960,
"ts": 105199545659.900,
"args":{}},{
"cat": "function",
"dur": 2389,
"name": "__cdecl fe::LayerStack::~LayerStack(void)",
"ph": "X",
"pid": 0,
"tid": 27960,
"ts": 105199543795.700,
"args":{}},{
"cat": "function",
"dur": 24059,
"name": "glfwDestroyWindow()",
"ph": "X",
"pid": 0,
"tid": 27960,
"ts": 105199546507.100,
"args":{}},{
"cat": "function",
"dur": 7587,
"name": "glfwTerminate()",
"ph": "X",
"pid": 0,
"tid": 27960,
"ts": 105199570651.000,
"args":{}},{
"cat": "function",
"dur": 32093,
"name": "void __cdecl fe::Win32Window::ShutDown(void)",
"ph": "X",
"pid": 0,
"tid": 27960,
"ts": 105199546228.800,
"args":{}},{
"cat": "function",
"dur": 32135,
"name": "__cdecl fe::Win32Window::~Win32Window(void)",
"ph": "X",
"pid": 0,
"tid": 27960,
"ts": 105199546228.600,
"args":{}}]}