{"otherdata": {}, "traceEvents": [ {},{
"cat": "function",
"dur": 0,
"name": "__cdecl fe::Application::~Application(void)",
"ph": "X",
"pid": 0,
"tid": 38592,
"ts": 351318169505.000
},{
"cat": "function",
"dur": 5,
"name": "__cdecl fe::OpenGLShader::~OpenGLShader(void)",
"ph": "X",
"pid": 0,
"tid": 38592,
"ts": 351318182043.200
},{
"cat": "function",
"dur": 4,
"name": "__cdecl fe::OpenGLVertexArray::~OpenGLVertexArray(void)",
"ph": "X",
"pid": 0,
"tid": 38592,
"ts": 351318182120.100
},{
"cat": "function",
"dur": 1,
"name": "__cdecl fe::OpenGLShader::~OpenGLShader(void)",
"ph": "X",
"pid": 0,
"tid": 38592,
"ts": 351318182165.700
},{
"cat": "function",
"dur": 1,
"name": "__cdecl fe::OpenGLVertexArray::~OpenGLVertexArray(void)",
"ph": "X",
"pid": 0,
"tid": 38592,
"ts": 351318182196.000
},{
"cat": "function",
"dur": 12643,
"name": "__cdecl fe::LayerStack::~LayerStack(void)",
"ph": "X",
"pid": 0,
"tid": 38592,
"ts": 351318169601.000
},{
"cat": "function",
"dur": 21687,
"name": "lfwDestroyWindow()",
"ph": "X",
"pid": 0,
"tid": 38592,
"ts": 351318182552.500
},{
"cat": "function",
"dur": 4695,
"name": "glfwTerminate()",
"ph": "X",
"pid": 0,
"tid": 38592,
"ts": 351318204385.100
},{
"cat": "function",
"dur": 26852,
"name": "void __cdecl fe::Win10Window::ShutDown(void)",
"ph": "X",
"pid": 0,
"tid": 38592,
"ts": 351318182300.400
},{
"cat": "function",
"dur": 26890,
"name": "__cdecl fe::Win10Window::~Win10Window(void)",
"ph": "X",
"pid": 0,
"tid": 38592,
"ts": 351318182300.100
}]}